shp2jvmapgen/__init__.py
shp2jvmapgen/bound2pixel.py
shp2jvmapgen/shp2jvmap.py
shp2jvmapgen/svg2jvm.py
shp2jvmapgen-0.0.2.dist-info/METADATA
shp2jvmapgen-0.0.2.dist-info/WHEEL
shp2jvmapgen-0.0.2.dist-info/RECORD
