Metadata-Version: 2.1
Name: shp2jvmapgen
Version: 0.0.2
Summary: Library for generating Jvectormap based maps from shapefiles and geojson, Works on Python 3
Project-URL: Homepage, https://github.com/waizaq/shp2jvmapgen
Project-URL: Bug Tracker, https://github.com/waizaq/shp2jvmapgen/issues
Author-email: Waiz Al Qorni <waiz.aq21@gmail.com>
Classifier: License :: OSI Approved :: MIT License
Classifier: Operating System :: OS Independent
Classifier: Programming Language :: Python :: 3
Requires-Python: >=3.7
Requires-Dist: beautifulsoup4>=4.11.1
Requires-Dist: fiona>=1.9.0
Requires-Dist: pyshp>=2.3.1
